blockies.py
blockies-0.0.4.dist-info/LICENSE
blockies-0.0.4.dist-info/METADATA
blockies-0.0.4.dist-info/WHEEL
blockies-0.0.4.dist-info/top_level.txt
blockies-0.0.4.dist-info/RECORD
